stara_cpp/__init__.py
stara_cpp-0.1.2.dist-info/METADATA
stara_cpp-0.1.2.dist-info/WHEEL
stara_cpp-0.1.2.dist-info/RECORD
