Metadata-Version: 2.1
Name: stara-cpp
Version: 0.1.2
Summary: A* pathfinding algorithm implementation in C++
Author: Valerius Mattfeld
Author-email: mail@valerius.me
Requires-Python: >=3.12.0,<4.0.0
Classifier: Programming Language :: Python :: 3
Classifier: Programming Language :: Python :: 3.12
Requires-Dist: numpy (==2.1.3)
